{
  "experiment_date": "2025-05-21T17:25:01.185479",
  "experiment_focus": "Dirty Dataset Comparison (Experiment 3: D3, T3, M3, C3)",
  "datasets_provided": {
    "ibm_raw_reference_csv": "data/ibm_dataset.csv",
    "dirty_dataset_csv": "data/ibm_dataset_dirty.csv"
  },
  "baseline": {
    "dirty_ibm": {
      "pipeline_type": "baseline",
      "acquired_data_path": "results/experiment_3/baseline/dirty_ibm/01_dirty_ibm_acquired_data.csv",
      "preprocessed_data_path": "results/experiment_3/baseline/dirty_ibm/02_dirty_ibm_preprocessed_data.csv",
      "engineered_data_path": "results/experiment_3/baseline/dirty_ibm/03_dirty_ibm_engineered_features.csv",
      "feature_selector_path": "results/experiment_1/baseline/ibm/artifacts/feature_selector.pkl",
      "expected_cols_path": "results/experiment_1/baseline/ibm/artifacts/expected_cols.json",
      "model_trained": false,
      "model_path": "results/experiment_3/baseline/dirty_ibm/artifacts",
      "evaluation_summary_path": "results/experiment_3/baseline/dirty_ibm/evaluation_summary.json",
      "Accuracy": 0.9326530612244898,
      "Precision (Weighted)": 0.9308981351161155,
      "Recall (Weighted)": 0.9326530612244898,
      "F1 Score (Weighted)": 0.9283302754044443,
      "ROC AUC": 0.9634728510271336,
      "Confusion Matrix": [
        [
          1215,
          18
        ],
        [
          81,
          156
        ]
      ],
      "Classification Report": {
        "0": {
          "precision": 0.9375,
          "recall": 0.9854014598540146,
          "f1-score": 0.9608540925266904,
          "support": 1233.0
        },
        "1": {
          "precision": 0.896551724137931,
          "recall": 0.6582278481012658,
          "f1-score": 0.759124087591241,
          "support": 237.0
        },
        "accuracy": 0.9326530612244898,
        "macro avg": {
          "precision": 0.9170258620689655,
          "recall": 0.8218146539776402,
          "f1-score": 0.8599890900589657,
          "support": 1470.0
        },
        "weighted avg": {
          "precision": 0.9308981351161155,
          "recall": 0.9326530612244898,
          "f1-score": 0.9283302754044443,
          "support": 1470.0
        }
      },
      "F1 Score": 0.9283302754044443
    }
  },
  "mlops": {
    "dirty_ibm": {
      "pipeline_type": "mlops",
      "acquired_data_path": "results/experiment_3/mlops/dirty_ibm/01_dirty_ibm_acquired_data.csv",
      "drift_status": "skipped_reference_data_not_found",
      "preprocessed_data_path": "results/experiment_3/mlops/dirty_ibm/02_dirty_ibm_preprocessed_data.csv",
      "engineered_data_path": "results/experiment_3/mlops/dirty_ibm/03_dirty_ibm_engineered_features.csv",
      "feature_selector_path_used": "results/experiment_3/mlops/dirty_ibm/artifacts/feature_selector.pkl",
      "expected_cols_path_used": "results/experiment_3/mlops/dirty_ibm/artifacts/expected_cols.json",
      "model_trained_this_run": true,
      "model_path": "results/experiment_3/mlops/dirty_ibm/artifacts",
      "evaluation_summary_path": "results/experiment_3/mlops/dirty_ibm/evaluation_summary.json",
      "Accuracy": 0.9693877551020408,
      "Precision (Weighted)": 0.9692073830629411,
      "Recall (Weighted)": 0.9693877551020408,
      "F1 Score (Weighted)": 0.9685681842933745,
      "ROC AUC": 0.9642359720896171,
      "Confusion Matrix": [
        [
          1225,
          8
        ],
        [
          37,
          200
        ]
      ],
      "Classification Report": {
        "0": {
          "precision": 0.9706814580031695,
          "recall": 0.9935117599351176,
          "f1-score": 0.9819639278557114,
          "support": 1233.0
        },
        "1": {
          "precision": 0.9615384615384616,
          "recall": 0.8438818565400844,
          "f1-score": 0.8988764044943821,
          "support": 237.0
        },
        "accuracy": 0.9693877551020408,
        "macro avg": {
          "precision": 0.9661099597708156,
          "recall": 0.918696808237601,
          "f1-score": 0.9404201661750468,
          "support": 1470.0
        },
        "weighted avg": {
          "precision": 0.9692073830629411,
          "recall": 0.9693877551020408,
          "f1-score": 0.9685681842933745,
          "support": 1470.0
        }
      },
      "F1 Score": 0.9685681842933745,
      "performance_log_path": "results/experiment_3/mlops/dirty_ibm/performance_log.json"
    }
  },
  "comparison": {
    "dirty_ibm": {
      "accuracy_diff": NaN,
      "f1_diff": NaN,
      "roc_auc_diff": NaN
    }
  },
  "mlops_metrics_dirty_run": {
    "drift_detected_in_this_run": false,
    "pipeline_duration_seconds": null
  }
}